mcp_3gpp_ftp/__init__.py
mcp_3gpp_ftp/server.py
mcp_3gpp_ftp-0.1.8.dist-info/METADATA
mcp_3gpp_ftp-0.1.8.dist-info/WHEEL
mcp_3gpp_ftp-0.1.8.dist-info/entry_points.txt
mcp_3gpp_ftp-0.1.8.dist-info/top_level.txt
mcp_3gpp_ftp-0.1.8.dist-info/RECORD
