Metadata-Version: 2.4
Name: mcp-3gpp-ftp
Version: 0.1.8
Summary: A FastMCP-based server for browsing 3GPP FTP website
Author-email: jamesco686@gmail.com
Requires-Python: >=3.10
Requires-Dist: beautifulsoup4>=4.13.4
Requires-Dist: mcp[cli]>=1.7.0
Requires-Dist: openpyxl>=3.1.5
Requires-Dist: pandas>=2.2.3
Requires-Dist: python-docx>=1.1.2
Requires-Dist: requests>=2.32.3
Requires-Dist: PyPDF2>=3.0.0
Requires-Dist: build>=1.2.2.post1
Requires-Dist: twine>=6.1.0
